<annotation>
	<folder>haze_detection</folder>
	<filename>BJ_Baidu_207.png</filename>
	<size>
		<width>457</width>
		<height>375</height>
		<depth>3</depth>
	</size>
	<segmented>0</segmented>
	<object>
		<name>car</name>
		<pose>Unspecified</pose>
		<truncated>0</truncated>
		<difficult>0</difficult>
		<bndbox>
			<xmin>260</xmin>
			<ymin>232</ymin>
			<xmax>384</xmax>
			<ymax>343</ymax>
		</bndbox>
	</object>
	<object>
		<name>car</name>
		<pose>Unspecified</pose>
		<truncated>0</truncated>
		<difficult>0</difficult>
		<bndbox>
			<xmin>15</xmin>
			<ymin>243</ymin>
			<xmax>175</xmax>
			<ymax>337</ymax>
		</bndbox>
	</object>
	<object>
		<name>car</name>
		<pose>Unspecified</pose>
		<truncated>0</truncated>
		<difficult>0</difficult>
		<bndbox>
			<xmin>156</xmin>
			<ymin>251</ymin>
			<xmax>213</xmax>
			<ymax>296</ymax>
		</bndbox>
	</object>
	<object>
		<name>car</name>
		<pose>Unspecified</pose>
		<truncated>0</truncated>
		<difficult>0</difficult>
		<bndbox>
			<xmin>249</xmin>
			<ymin>248</ymin>
			<xmax>299</xmax>
			<ymax>297</ymax>
		</bndbox>
	</object>
	<object>
		<name>car</name>
		<pose>Unspecified</pose>
		<truncated>0</truncated>
		<difficult>0</difficult>
		<bndbox>
			<xmin>208</xmin>
			<ymin>252</ymin>
			<xmax>239</xmax>
			<ymax>275</ymax>
		</bndbox>
	</object>
	<object>
		<name>car</name>
		<pose>Unspecified</pose>
		<truncated>1</truncated>
		<difficult>0</difficult>
		<bndbox>
			<xmin>1</xmin>
			<ymin>240</ymin>
			<xmax>90</xmax>
			<ymax>302</ymax>
		</bndbox>
	</object>
	<object>
		<name>car</name>
		<pose>Unspecified</pose>
		<truncated>1</truncated>
		<difficult>0</difficult>
		<bndbox>
			<xmin>421</xmin>
			<ymin>257</ymin>
			<xmax>457</xmax>
			<ymax>343</ymax>
		</bndbox>
	</object>
	<object>
		<name>car</name>
		<pose>Unspecified</pose>
		<truncated>0</truncated>
		<difficult>1</difficult>
		<bndbox>
			<xmin>234</xmin>
			<ymin>250</ymin>
			<xmax>256</xmax>
			<ymax>269</ymax>
		</bndbox>
	</object>
	<object>
		<name>car</name>
		<pose>Unspecified</pose>
		<truncated>0</truncated>
		<difficult>1</difficult>
		<bndbox>
			<xmin>417</xmin>
			<ymin>249</ymin>
			<xmax>452</xmax>
			<ymax>266</ymax>
		</bndbox>
	</object>
</annotation>