<annotation verified="no">
	<folder>haze_detection</folder>
	<filename>GSGL_Google_371.png</filename>
	<size>
		<width>500</width>
		<height>326</height>
		<depth>3</depth>
	</size>
	<segmented>0</segmented>
	<object>
		<name>car</name>
		<pose>Unspecified</pose>
		<truncated>0</truncated>
		<difficult>0</difficult>
		<inferred>0</inferred>
		<bndbox>
			<xmin>74</xmin>
			<ymin>154</ymin>
			<xmax>206</xmax>
			<ymax>251</ymax>
		</bndbox>
	</object>
	<object>
		<name>bus</name>
		<pose>Unspecified</pose>
		<truncated>0</truncated>
		<difficult>0</difficult>
		<inferred>0</inferred>
		<bndbox>
			<xmin>337</xmin>
			<ymin>63</ymin>
			<xmax>447</xmax>
			<ymax>212</ymax>
		</bndbox>
	</object>
</annotation>