<annotation>
	<folder>haze_detection</folder>
	<filename>HEB_Google_644.png</filename>
	<size>
		<width>853</width>
		<height>600</height>
		<depth>3</depth>
	</size>
	<segmented>0</segmented>
	<object>
		<name>person</name>
		<pose>Unspecified</pose>
		<truncated>0</truncated>
		<difficult>0</difficult>
		<bndbox>
			<xmin>394</xmin>
			<ymin>158</ymin>
			<xmax>511</xmax>
			<ymax>465</ymax>
		</bndbox>
	</object>
	<object>
		<name>bicycle</name>
		<pose>Unspecified</pose>
		<truncated>0</truncated>
		<difficult>0</difficult>
		<bndbox>
			<xmin>404</xmin>
			<ymin>290</ymin>
			<xmax>503</xmax>
			<ymax>495</ymax>
		</bndbox>
	</object>
	<object>
		<name>car</name>
		<pose>Unspecified</pose>
		<truncated>0</truncated>
		<difficult>0</difficult>
		<bndbox>
			<xmin>16</xmin>
			<ymin>204</ymin>
			<xmax>192</xmax>
			<ymax>329</ymax>
		</bndbox>
	</object>
</annotation>